LICENSE.txt
SPaG-1.0.0a0.data/scripts/spag_cli
SPaG-1.0.0a0.dist-info/METADATA
SPaG-1.0.0a0.dist-info/RECORD
SPaG-1.0.0a0.dist-info/WHEEL
SPaG-1.0.0a0.dist-info/top_level.txt
SPaG-1.0.0a0.dist-info/zip-safe
spag/__init__.py
spag/generator.py
spag/parser.py
spag/scanner.py
spag/generators/__init__.py
spag/generators/c.py
spag/generators/go.py
spag/generators/python.py
