Metadata-Version: 2.1
Name: SPaG
Version: 1.0.0a0
Summary: A module containing scanner (regular expression) and parser (BNF) compilers as well as a base generator, which provides protection and validation, from which all target language generators must inherit from. A script is also included which reads the respective specification(s) from file and outputs the resulting code to disk.
Home-page: https://github.com/rrozansk/SPaG
Author: Ryan Rozanski
Author-email: 
Maintainer: Ryan Rozanski
Maintainer-email: 
License: MIT
Download-URL: https://github.com/rrozansk/SPaG
Keywords: abstract-syntax-tree ast AST Backus-Naur-form Backus-normal-form bnf BNF command-line-interface cli CLI code-generation compiler context-free-grammar deterministic-finite-automaton dfa DFA dfa-minimization direct-encoding finite-state-machine first-set follow-set fsm FSM lexeme lexer lexer-generator lexical-analysis ll1 LL1 LL(1) longest-match maximal-munch nfa NFA nondeterministic-finite-automaton nonterminal(s) parser parser-generator production-rule(s) regular-expression(s) regular-
Platform: UNKNOWN
Classifier: Development Status :: 3 - Alpha
Classifier: Environment :: Console
Classifier: Intended Audience :: Developers
Classifier: Intended Audience :: Education
Classifier: Intended Audience :: End Users/Desktop
Classifier: Intended Audience :: Science/Research
Classifier: License :: OSI Approved :: MIT License
Classifier: Natural Language :: English
Classifier: Operating System :: OS Independent
Classifier: Programming Language :: Python
Classifier: Programming Language :: Python :: 2
Classifier: Programming Language :: Python :: 2.7
Classifier: Programming Language :: Python :: 3
Classifier: Programming Language :: Python :: 3.0
Classifier: Programming Language :: Python :: 3.1
Classifier: Programming Language :: Python :: 3.2
Classifier: Programming Language :: Python :: 3.3
Classifier: Programming Language :: Python :: 3.4
Classifier: Programming Language :: Python :: 3.5
Classifier: Programming Language :: Python :: 3.6
Classifier: Programming Language :: Python :: 3.7
Classifier: Topic :: Scientific/Engineering
Classifier: Topic :: Software Development
Classifier: Topic :: Software Development :: Build Tools
Classifier: Topic :: Software Development :: Code Generators
Classifier: Topic :: Software Development :: Compilers
Classifier: Topic :: Text Processing
Classifier: Topic :: Text Processing :: Linguistic
Requires-Python: >= 2.7.0
